test/__init__.py
test/test_http.py
test/test_redis_session_store.py
tokenserver/__init__.py
tokenserver/main.py
tokenserver/redis_session_store.py
datashare_network_tokenserver-0.1.2.dist-info/LICENSE
datashare_network_tokenserver-0.1.2.dist-info/METADATA
datashare_network_tokenserver-0.1.2.dist-info/WHEEL
datashare_network_tokenserver-0.1.2.dist-info/top_level.txt
datashare_network_tokenserver-0.1.2.dist-info/RECORD
