Metadata-Version: 2.1
Name: datashare-network-tokenserver
Version: 0.1.2
Summary: Datashare Network Token Server
Home-page: https://github.com/icij/datashare-network-tokenserver
License: UNKNOWN
Keywords: datashare,server,network,cryptography,authentication
Platform: UNKNOWN
Classifier: Programming Language :: Python :: 3
Classifier: Programming Language :: Python :: 3.7
Classifier: Programming Language :: Python :: 3.8
Classifier: Programming Language :: Python :: 3.9
Classifier: Programming Language :: Python :: 3.10
Classifier: Intended Audience :: Developers
Classifier: License :: OSI Approved :: GNU Affero General Public License v3
Classifier: Operating System :: OS Independent
Classifier: Topic :: Security :: Cryptography
Requires-Python: >=3.7
License-File: LICENSE
Requires-Dist: aioredis (==2.0.1)
Requires-Dist: sscred (==0.2.1)
Requires-Dist: starlette
Requires-Dist: uvicorn[standard]
